validator/__init__.py
validator/index.py
x24109487_validator-0.0.2.dist-info/licenses/LICENSE
x24109487_validator-0.0.2.dist-info/METADATA
x24109487_validator-0.0.2.dist-info/WHEEL
x24109487_validator-0.0.2.dist-info/top_level.txt
x24109487_validator-0.0.2.dist-info/RECORD
