Metadata-Version: 2.4
Name: x24109487_validator
Version: 0.0.2
Summary: A library is a lightweight Python package with key focus to handle data validation on primitive and non primitive data types in python.
Author-email: Okeke Chidiebube <x24109487@student.ncirl.ie>
Classifier: Programming Language :: Python :: 3
Classifier: Operating System :: OS Independent
Classifier: License :: OSI Approved :: MIT License
Requires-Python: >=3.8
License-File: LICENSE
Dynamic: license-file
